README.md
pyproject.toml
setup.cfg
setup.py
baseapp_chats/__init__.py
baseapp_chats/admin.py
baseapp_chats/apps.py
baseapp_chats/base.py
baseapp_chats/models.py
baseapp_chats/permissions.py
baseapp_chats/triggers.py
baseapp_chats/utils.py
baseapp_chats.egg-info/PKG-INFO
baseapp_chats.egg-info/SOURCES.txt
baseapp_chats.egg-info/dependency_links.txt
baseapp_chats.egg-info/requires.txt
baseapp_chats.egg-info/top_level.txt
baseapp_chats/graphql/__init__.py
baseapp_chats/graphql/filters.py
baseapp_chats/graphql/interfaces.py
baseapp_chats/graphql/mutations.py
baseapp_chats/graphql/object_types.py
baseapp_chats/graphql/queries.py
baseapp_chats/graphql/subscriptions.py
baseapp_chats/migrations/0001_initial.py
baseapp_chats/migrations/0002_message_set_last_message_and_more.py
baseapp_chats/migrations/0003_alter_unreadmessagecount_room.py
baseapp_chats/migrations/0004_chatroomparticipant_has_archived_room.py
baseapp_chats/migrations/0005_remove_messagestatus_increment_unread_count_and_more.py
baseapp_chats/migrations/0006_remove_messagestatus_increment_unread_count_and_more.py
baseapp_chats/migrations/0007_messagestatus_increment_unread_count.py
baseapp_chats/migrations/0008_alter_chatroomparticipant_options.py
baseapp_chats/migrations/0009_remove_message_create_message_status_and_more.py
baseapp_chats/migrations/0010_message_deleted.py
baseapp_chats/migrations/__init__.py
baseapp_chats/tests/__init__.py
baseapp_chats/tests/conftest.py
baseapp_chats/tests/factories.py
baseapp_chats/tests/test_graphql_mutations.py
baseapp_chats/tests/test_graphql_queries.py
baseapp_chats/tests/test_graphql_subscriptions.py
baseapp_chats/tests/test_migration_health_check.py
baseapp_chats/tests/test_utils.py
testproject/__init__.py
testproject/graphql.py
testproject/settings.py
testproject/setup.py
testproject/urls.py
testproject/wsgi.py