Metadata-Version: 2.1
Name: baseapp-chats
Version: 0.1.16
Summary: BaseApp Chats
Home-page: https://github.com/silverlogic/baseapp-backend
Author: The SilverLogic
Author-email: dev@tsl.io
License: BSD-3-Clause  # Example license
Platform: UNKNOWN
Requires-Python: >=3.8
